commons_system/__init__.py
commons_system/exceptions.py
commons_system/info/__init__.py
commons_system/models/__init__.py
commons_system/models/process.py
commons_system/models/software.py
commons_system/monitor/__init__.py
commons_system/platform/__init__.py
commons_system/platform/linux/__init__.py
commons_system/platform/mac/__init__.py
commons_system/platform/windows/__init__.py
commons_system/platform/windows/filesystem.py
commons_system/platform/windows/process.py
commons_system/platform/windows/registry.py
commons_system/platform/windows/shortcut.py
commons_system/platform/windows/software.py
commons_system-0.1.0.dist-info/METADATA
commons_system-0.1.0.dist-info/WHEEL
commons_system-0.1.0.dist-info/top_level.txt
commons_system-0.1.0.dist-info/RECORD
