Metadata-Version: 2.4
Name: commons-system
Version: 0.1.0
Summary: Add your description here
Requires-Python: >=3.10
Requires-Dist: loguru>=0.7.3
Requires-Dist: psutil>=7.0.0
Requires-Dist: pywin32>=310
